qamar.cpython-36m-x86_64-linux-gnu.so
qamar.libs/liblua-5-6fd9cbb6.3.so
qamar-0.1.0.dist-info/METADATA
qamar-0.1.0.dist-info/top_level.txt
qamar-0.1.0.dist-info/RECORD
qamar-0.1.0.dist-info/WHEEL
