Metadata-Version: 2.1
Name: qamar
Version: 0.1.0
Summary: A lua binding for python
Home-page: UNKNOWN
Author: Aurora Zuoris
Author-email: programming.aurora@gmail.com
License: UNKNOWN
Platform: UNKNOWN
